[
  {
    "project": "rotki/rotki",
    "commit": "a3a4be246597c9a41f5d9980c26f2f76953f7bab",
    "filename": "rotkehlchen/rotkehlchen.py",
    "filename_after_commit": "/home/chowyi/TypeAnnotation_Study/GitHub/rotki-rotki/rotkehlchen/rotkehlchen.py",
    "file_hunks_size": 1,
    "min_patch_found": false,
    "single_hunk": false,
    "fit_TFix": false,
    "delete_only_patch": false,
    "has_suppression_all_hunks": false,
    "full_warning_msg": "rotkehlchen/rotkehlchen.py:400:60 Incompatible parameter type [6]: Expected `rotkehlchen.typing.FiatAsset` for 2nd positional only parameter to call `Inquirer.query_fiat_pair` but got `str`.",
    "message": " Expected `rotkehlchen.typing.FiatAsset` for 2nd positional only parameter to call `Inquirer.query_fiat_pair` but got `str`.",
    "rule_id": "Incompatible parameter type [6]",
    "warning_line_no": 400,
    "warning_line": "            usd_rate = Inquirer().query_fiat_pair(currency, 'USD')"
  }
]