[
  {
    "project": "pantsbuild/pants",
    "commit": "edd039bf98702f3eb01a7cd4e25559247e686a72",
    "filename": "src/python/pants/engine/engine.py",
    "min_patch_found": false,
    "full_warning_msg": "src/python/pants/engine/engine.py:30:15 Invalid type [31]: Expression `pants.util.objects.datatype(\"Result\", [\"error\", \"root_products\"])` is not a valid type.",
    "exception": "[Errno 2] No such file or directory: '/home/chowyi/TypeAnnotation_Study/GitHub/pantsbuild-pants/src/python/pants/engine/engine.py'",
    "dd_fail": true
  }
]