[
  {
    "project": "samuelcolvin/pydantic",
    "commit": "6c0f4f31d1c4bdafde4a8f3d365639a8e22609a0",
    "filename": "tests/mypy_test_fails1.py",
    "min_patch_found": false,
    "full_warning_msg": "tests/mypy_test_fails1.py:20:14 Unsupported operand [58]: `+` is not supported for operand types `int` and `str`.",
    "exception": "PatchSet should only have 1 Patch, but it has 0",
    "dd_fail": true
  },
  {
    "project": "samuelcolvin/pydantic",
    "commit": "6c0f4f31d1c4bdafde4a8f3d365639a8e22609a0",
    "filename": "tests/mypy_test_success.py",
    "min_patch_found": false,
    "full_warning_msg": "tests/mypy_test_success.py:50:19 Incompatible parameter type [6]: Expected `datetime` for 1st positional only parameter to call `day_of_week` but got `Optional[datetime]`.",
    "exception": "PatchSet should only have 1 Patch, but it has 0",
    "dd_fail": true
  }
]