[
  {
    "project": "lxneng/xpinyin",
    "commit": "caaca557fccfa4ebdab77ede282b4a0ef1cb6480",
    "filename": "src/xpinyin/__init__.py",
    "filename_after_commit": "/home/chowyi/TypeAnnotation_Study/GitHub/lxneng-xpinyin/src/xpinyin/__init__.py",
    "file_hunks_size": 1,
    "min_patch_found": false,
    "single_hunk": false,
    "fit_TFix": false,
    "delete_only_patch": false,
    "has_suppression_all_hunks": false,
    "full_warning_msg": "src/xpinyin/__init__.py:60:28 Incompatible parameter type [6]: Expected `_typeshed.SupportsKeysAndGetItem[Variable[_KT], Variable[_VT]]` for 1st positional only parameter to call `dict.__init__` but got `typing.Generator[typing.Tuple[typing.Any, ...], None, None]`.",
    "message": " Expected `_typeshed.SupportsKeysAndGetItem[Variable[_KT], Variable[_VT]]` for 1st positional only parameter to call `dict.__init__` but got `typing.Generator[typing.Tuple[typing.Any, ...], None, None]`.",
    "rule_id": "Incompatible parameter type [6]",
    "warning_line_no": 60,
    "warning_line": "        self.pinyins = dict(tuple(line.split('\\t', maxsplit=1)) for line in data_path.read_text().splitlines())"
  }
]